loralib/__init__.py
loralib/layers.py
loralib/utils.py
loralib-0.1.1.dist-info/METADATA
loralib-0.1.1.dist-info/WHEEL
loralib-0.1.1.dist-info/top_level.txt
loralib-0.1.1.dist-info/RECORD
