Metadata-Version: 2.1
Name: loralib
Version: 0.1.1
Summary: PyTorch implementation of low-rank adaptation (LoRA), a parameter-efficient approach to adapt a large pre-trained deep learning model which obtains performance on-par with full model fine-tuning.
Home-page: https://github.com/microsoft/LoRA
Author: Edward J. Hu, Yelong Shen, Phillip Wallis, Zeyuan Allen-Zhu, Yuanzhi Li, Shean Wang, Lu Wang, Weizhu Chen
Author-email: edward.hu@microsoft.com
License: UNKNOWN
Platform: UNKNOWN
Classifier: Programming Language :: Python :: 3
Classifier: License :: OSI Approved :: MIT License
Classifier: Operating System :: OS Independent
Requires-Python: >=3.6
